{
  "ts": "2026-05-06T02:32:05.501932+09:00",
  "start_date": "2026-04-24",
  "status": "running",
  "equity": 986.69,
  "available": 718.28,
  "unrealized": -6.98,
  "daily_pnl": 0.96,
  "total_pnl": -13.31,
  "cum_pct": -1.33,
  "daily_avg_pct": -0.1029,
  "annual_pct": -31.32,
  "mdd": -7.52,
  "current_dd": -6.07,
  "seed_used": 268.41,
  "seed_used_pct": 27.2,
  "long_count": 7,
  "short_count": 7,
  "positions": [
    {
      "symbol": "DOTUSDT",
      "side": "SHORT",
      "pnl": -2.53,
      "pnl_pct": -0.35,
      "margin": 71.81,
      "leverage": "10",
      "tier": "8/9",
      "entry": 1.2614,
      "mark": 1.2659
    },
    {
      "symbol": "AVAXUSDT",
      "side": "SHORT",
      "pnl": -0.52,
      "pnl_pct": -0.22,
      "margin": 30.23,
      "leverage": "8",
      "tier": "7/10",
      "entry": 9.3548,
      "mark": 9.375
    },
    {
      "symbol": "TRXUSDT",
      "side": "SHORT",
      "pnl": -1.21,
      "pnl_pct": -0.8,
      "margin": 17.05,
      "leverage": "9",
      "tier": "3/9",
      "entry": 0.3412,
      "mark": 0.344
    },
    {
      "symbol": "ADAUSDT",
      "side": "SHORT",
      "pnl": -1.35,
      "pnl_pct": -1.25,
      "margin": 15.65,
      "leverage": "7",
      "tier": "4/9",
      "entry": 0.2545,
      "mark": 0.2577
    },
    {
      "symbol": "WLFIUSDT",
      "side": "SHORT",
      "pnl": -0.71,
      "pnl_pct": -0.74,
      "margin": 12.14,
      "leverage": "8",
      "tier": "4/10",
      "entry": 0.0645,
      "mark": 0.0649
    },
    {
      "symbol": "BTCUSDT",
      "side": "LONG",
      "pnl": 0.44,
      "pnl_pct": 0.55,
      "margin": 11.61,
      "leverage": "7",
      "tier": "2/9",
      "entry": 80831.1,
      "mark": 81271.67
    },
    {
      "symbol": "ZECUSDT",
      "side": "SHORT",
      "pnl": -1.37,
      "pnl_pct": -1.89,
      "margin": 10.51,
      "leverage": "7",
      "tier": "4/11",
      "entry": 424.8788,
      "mark": 432.91
    },
    {
      "symbol": "TAOUSDT",
      "side": "LONG",
      "pnl": -0.09,
      "pnl_pct": -0.25,
      "margin": 5.8,
      "leverage": "6",
      "tier": "3/10",
      "entry": 283.7413,
      "mark": 283.03
    },
    {
      "symbol": "SUIUSDT",
      "side": "LONG",
      "pnl": -0.01,
      "pnl_pct": -0.04,
      "margin": 4.79,
      "leverage": "6",
      "tier": "3/9",
      "entry": 0.959,
      "mark": 0.9586
    },
    {
      "symbol": "LINKUSDT",
      "side": "SHORT",
      "pnl": 0.43,
      "pnl_pct": 1.18,
      "margin": 3.98,
      "leverage": "9",
      "tier": "2/9",
      "entry": 9.793,
      "mark": 9.677
    },
    {
      "symbol": "BCHUSDT",
      "side": "LONG",
      "pnl": -0.07,
      "pnl_pct": -0.3,
      "margin": 3.24,
      "leverage": "7",
      "tier": "2/9",
      "entry": 455.2,
      "mark": 453.83
    },
    {
      "symbol": "ETHUSDT",
      "side": "LONG",
      "pnl": -0.05,
      "pnl_pct": -0.2,
      "margin": 2.95,
      "leverage": "8",
      "tier": "2/9",
      "entry": 2365.47,
      "mark": 2360.68
    },
    {
      "symbol": "SOLUSDT",
      "side": "LONG",
      "pnl": 0.23,
      "pnl_pct": 1.35,
      "margin": 2.44,
      "leverage": "7",
      "tier": "2/9",
      "entry": 84.17,
      "mark": 85.31
    },
    {
      "symbol": "ONDOUSDT",
      "side": "LONG",
      "pnl": -0.17,
      "pnl_pct": -1.24,
      "margin": 1.67,
      "leverage": "8",
      "tier": "1/12",
      "entry": 0.3224,
      "mark": 0.3184
    }
  ],
  "signals": {
    "AAVEUSDT": {
      "dir": "short",
      "conf": 0.533
    },
    "SUIUSDT": {
      "dir": "long",
      "conf": 0.525
    },
    "WLDUSDT": {
      "dir": "short",
      "conf": 0.517
    },
    "1000PEPEUSDT": {
      "dir": "short",
      "conf": 0.514
    },
    "ZECUSDT": {
      "dir": "short",
      "conf": 0.537
    },
    "HYPEUSDT": {
      "dir": "long",
      "conf": 0.504
    },
    "PENGUUSDT": {
      "dir": "short",
      "conf": 0.585
    },
    "ARBUSDT": {
      "dir": "short",
      "conf": 0.576
    },
    "ENAUSDT": {
      "dir": "short",
      "conf": 0.519
    },
    "SOLUSDT": {
      "dir": "long",
      "conf": 0.535
    },
    "BCHUSDT": {
      "dir": "long",
      "conf": 0.508
    },
    "DOTUSDT": {
      "dir": "short",
      "conf": 0.511
    },
    "XRPUSDT": {
      "dir": "short",
      "conf": 0.501
    },
    "TRXUSDT": {
      "dir": "short",
      "conf": 0.503
    },
    "BTCUSDT": {
      "dir": "short",
      "conf": 0.501
    },
    "BNBUSDT": {
      "dir": "short",
      "conf": 0.532
    },
    "TAOUSDT": {
      "dir": "long",
      "conf": 0.522
    },
    "ADAUSDT": {
      "dir": "short",
      "conf": 0.52
    },
    "LINKUSDT": {
      "dir": "short",
      "conf": 0.522
    },
    "AVAXUSDT": {
      "dir": "short",
      "conf": 0.853
    },
    "DOGEUSDT": {
      "dir": "short",
      "conf": 0.52
    },
    "NEARUSDT": {
      "dir": "short",
      "conf": 0.506
    },
    "ETHUSDT": {
      "dir": "long",
      "conf": 0.549
    },
    "STABLEUSDT": {
      "dir": "short",
      "conf": 0.592
    },
    "MUSDT": {
      "dir": "short",
      "conf": 0.541
    },
    "TRUMPUSDT": {
      "dir": "short",
      "conf": 0.541
    },
    "ASTERUSDT": {
      "dir": "short",
      "conf": 0.628
    },
    "XMRUSDT": {
      "dir": "short",
      "conf": 0.555
    },
    "LTCUSDT": {
      "dir": "long",
      "conf": 0.5
    },
    "APTUSDT": {
      "dir": "short",
      "conf": 0.696
    },
    "TONUSDT": {
      "dir": "short",
      "conf": 0.502
    },
    "WLFIUSDT": {
      "dir": "short",
      "conf": 0.575
    },
    "ONDOUSDT": {
      "dir": "long",
      "conf": 0.698
    },
    "DASHUSDT": {
      "dir": "long",
      "conf": 0.555
    }
  },
  "equity_hist": [
    {
      "t": "2026-04-24",
      "v": 4.29
    },
    {
      "t": "2026-04-25",
      "v": 3.41
    },
    {
      "t": "2026-04-26",
      "v": 5.17
    },
    {
      "t": "2026-04-27",
      "v": 16.74
    },
    {
      "t": "2026-04-28",
      "v": 6.68
    },
    {
      "t": "2026-04-29",
      "v": 20.27
    },
    {
      "t": "2026-04-30",
      "v": 29.64
    },
    {
      "t": "2026-05-01",
      "v": 48.25
    },
    {
      "t": "2026-05-02",
      "v": 48.07
    },
    {
      "t": "2026-05-03",
      "v": 43.0
    },
    {
      "t": "2026-05-04",
      "v": 10.37
    },
    {
      "t": "2026-05-05",
      "v": -19.42
    },
    {
      "t": "2026-05-06",
      "v": -13.31
    }
  ],
  "trade_history": [
    {
      "ts": "2026-05-06 00:22",
      "symbol": "BCHUSDT",
      "side": "Buy",
      "pnl": 0.96,
      "reason": "4/9"
    },
    {
      "ts": "2026-05-05 21:22",
      "symbol": "TRXUSDT",
      "side": "Sell",
      "pnl": 0.07,
      "reason": "3/9"
    },
    {
      "ts": "2026-05-05 19:45",
      "symbol": "BCHUSDT",
      "side": "Buy",
      "pnl": 1.08,
      "reason": "4/9"
    },
    {
      "ts": "2026-05-05 19:41",
      "symbol": "BCHUSDT",
      "side": "Buy",
      "pnl": 2.24,
      "reason": "L7"
    },
    {
      "ts": "2026-05-05 19:22",
      "symbol": "LINKUSDT",
      "side": "Sell",
      "pnl": -0.01,
      "reason": "마진 0.1USDT < 1"
    },
    {
      "ts": "2026-05-05 19:18",
      "symbol": "LINKUSDT",
      "side": "Sell",
      "pnl": -0.55,
      "reason": "2/12"
    },
    {
      "ts": "2026-05-05 15:14",
      "symbol": "LINKUSDT",
      "side": "Buy",
      "pnl": 0.63,
      "reason": "3/12"
    },
    {
      "ts": "2026-05-05 15:00",
      "symbol": "LINKUSDT",
      "side": "Buy",
      "pnl": 0.75,
      "reason": "4/12"
    },
    {
      "ts": "2026-05-05 11:00",
      "symbol": "DASHUSDT",
      "side": "Sell",
      "pnl": 0.07,
      "reason": "1/12"
    },
    {
      "ts": "2026-05-05 08:30",
      "symbol": "DASHUSDT",
      "side": "Sell",
      "pnl": 0.01,
      "reason": "L2"
    },
    {
      "ts": "2026-05-05 08:25",
      "symbol": "DASHUSDT",
      "side": "Sell",
      "pnl": 0.79,
      "reason": "7/12"
    },
    {
      "ts": "2026-05-05 08:15",
      "symbol": "DASHUSDT",
      "side": "Sell",
      "pnl": 0.45,
      "reason": "7/12"
    },
    {
      "ts": "2026-05-05 08:13",
      "symbol": "DASHUSDT",
      "side": "Sell",
      "pnl": 0.88,
      "reason": "-"
    },
    {
      "ts": "2026-05-05 05:08",
      "symbol": "ADAUSDT",
      "side": "Sell",
      "pnl": 0.48,
      "reason": "4/9"
    },
    {
      "ts": "2026-05-05 04:57",
      "symbol": "ONDOUSDT",
      "side": "Sell",
      "pnl": -68.0,
      "reason": "External Exit"
    },
    {
      "ts": "2026-05-05 04:09",
      "symbol": "LINKUSDT",
      "side": "Sell",
      "pnl": 0.01,
      "reason": "1/12"
    },
    {
      "ts": "2026-05-05 04:09",
      "symbol": "LINKUSDT",
      "side": "Sell",
      "pnl": 0.19,
      "reason": "1/12"
    },
    {
      "ts": "2026-05-05 03:41",
      "symbol": "LINKUSDT",
      "side": "Sell",
      "pnl": 0.17,
      "reason": "2/12"
    },
    {
      "ts": "2026-05-05 01:15",
      "symbol": "SOLUSDT",
      "side": "Buy",
      "pnl": 0.01,
      "reason": "2/9"
    },
    {
      "ts": "2026-05-05 01:04",
      "symbol": "DASHUSDT",
      "side": "Buy",
      "pnl": 0.42,
      "reason": "4/12"
    }
  ],
  "num_days": 13
}