{
  "ts": "2026-05-03T17:42:40.287971+09:00",
  "start_date": "2026-04-24",
  "status": "running",
  "equity": 1044.41,
  "available": 891.39,
  "unrealized": -0.01,
  "daily_pnl": -2.83,
  "total_pnl": 44.41,
  "cum_pct": 4.44,
  "daily_avg_pct": 0.4354,
  "annual_pct": 388.3,
  "mdd": -1.92,
  "current_dd": -0.6,
  "seed_used": 153.02,
  "seed_used_pct": 14.65,
  "long_count": 4,
  "short_count": 8,
  "positions": [
    {
      "symbol": "SOLUSDT",
      "side": "SHORT",
      "pnl": 0.73,
      "pnl_pct": 0.45,
      "margin": 15.93,
      "leverage": "10",
      "tier": "4/9",
      "entry": 84.2121,
      "mark": 83.83
    },
    {
      "symbol": "WLDUSDT",
      "side": "SHORT",
      "pnl": -1.2,
      "pnl_pct": -1.13,
      "margin": 15.35,
      "leverage": "7",
      "tier": "5/9",
      "entry": 0.236,
      "mark": 0.2387
    },
    {
      "symbol": "1000PEPEUSDT",
      "side": "LONG",
      "pnl": -0.38,
      "pnl_pct": -0.47,
      "margin": 11.4,
      "leverage": "7",
      "tier": "5/11",
      "entry": 0.004,
      "mark": 0.0039
    },
    {
      "symbol": "ZECUSDT",
      "side": "SHORT",
      "pnl": -1.74,
      "pnl_pct": -2.44,
      "margin": 10.48,
      "leverage": "7",
      "tier": "3/9",
      "entry": 376.7653,
      "mark": 385.94
    },
    {
      "symbol": "ONDOUSDT",
      "side": "SHORT",
      "pnl": 1.45,
      "pnl_pct": 2.37,
      "margin": 9.99,
      "leverage": "6",
      "tier": "4/10",
      "entry": 0.2868,
      "mark": 0.28
    },
    {
      "symbol": "XRPUSDT",
      "side": "LONG",
      "pnl": 0.0,
      "pnl_pct": 0.0,
      "margin": 7.44,
      "leverage": "8",
      "tier": "3/9",
      "entry": 1.3866,
      "mark": 1.3867
    },
    {
      "symbol": "SUIUSDT",
      "side": "LONG",
      "pnl": 0.19,
      "pnl_pct": 0.41,
      "margin": 6.55,
      "leverage": "7",
      "tier": "2/9",
      "entry": 0.9131,
      "mark": 0.9169
    },
    {
      "symbol": "APTUSDT",
      "side": "SHORT",
      "pnl": 0.03,
      "pnl_pct": 0.06,
      "margin": 6.24,
      "leverage": "7",
      "tier": "3/9",
      "entry": 0.9807,
      "mark": 0.9801
    },
    {
      "symbol": "MUSDT",
      "side": "SHORT",
      "pnl": -0.14,
      "pnl_pct": -0.35,
      "margin": 4.83,
      "leverage": "8",
      "tier": "3/10",
      "entry": 2.9629,
      "mark": 2.9733
    },
    {
      "symbol": "DOTUSDT",
      "side": "SHORT",
      "pnl": 0.66,
      "pnl_pct": 2.03,
      "margin": 4.0,
      "leverage": "8",
      "tier": "1/9",
      "entry": 1.238,
      "mark": 1.2129
    },
    {
      "symbol": "TONUSDT",
      "side": "LONG",
      "pnl": -0.01,
      "pnl_pct": -0.02,
      "margin": 3.51,
      "leverage": "7",
      "tier": "2/9",
      "entry": 1.3353,
      "mark": 1.335
    },
    {
      "symbol": "BCHUSDT",
      "side": "SHORT",
      "pnl": 0.39,
      "pnl_pct": 1.73,
      "margin": 2.77,
      "leverage": "8",
      "tier": "2/9",
      "entry": 451.6,
      "mark": 443.8
    }
  ],
  "signals": {
    "AAVEUSDT": {
      "dir": "short",
      "conf": 0.51
    },
    "SUIUSDT": {
      "dir": "short",
      "conf": 0.856
    },
    "WLDUSDT": {
      "dir": "short",
      "conf": 0.758
    },
    "1000PEPEUSDT": {
      "dir": "short",
      "conf": 0.52
    },
    "ZECUSDT": {
      "dir": "short",
      "conf": 0.524
    },
    "HYPEUSDT": {
      "dir": "long",
      "conf": 0.52
    },
    "PENGUUSDT": {
      "dir": "long",
      "conf": 0.639
    },
    "ARBUSDT": {
      "dir": "short",
      "conf": 0.643
    },
    "ENAUSDT": {
      "dir": "short",
      "conf": 0.522
    },
    "SOLUSDT": {
      "dir": "short",
      "conf": 0.991
    },
    "BCHUSDT": {
      "dir": "short",
      "conf": 0.754
    },
    "DOTUSDT": {
      "dir": "short",
      "conf": 0.726
    },
    "XRPUSDT": {
      "dir": "short",
      "conf": 0.627
    },
    "TRXUSDT": {
      "dir": "short",
      "conf": 0.611
    },
    "BTCUSDT": {
      "dir": "short",
      "conf": 0.504
    },
    "BNBUSDT": {
      "dir": "short",
      "conf": 0.501
    },
    "TAOUSDT": {
      "dir": "short",
      "conf": 0.629
    },
    "ADAUSDT": {
      "dir": "short",
      "conf": 0.885
    },
    "LINKUSDT": {
      "dir": "short",
      "conf": 0.523
    },
    "AVAXUSDT": {
      "dir": "short",
      "conf": 0.529
    },
    "DOGEUSDT": {
      "dir": "long",
      "conf": 0.66
    },
    "NEARUSDT": {
      "dir": "short",
      "conf": 0.506
    },
    "ETHUSDT": {
      "dir": "short",
      "conf": 0.501
    },
    "STABLEUSDT": {
      "dir": "short",
      "conf": 0.592
    },
    "MUSDT": {
      "dir": "long",
      "conf": 0.525
    },
    "TRUMPUSDT": {
      "dir": "short",
      "conf": 0.549
    },
    "ASTERUSDT": {
      "dir": "short",
      "conf": 0.628
    },
    "XMRUSDT": {
      "dir": "short",
      "conf": 0.555
    },
    "LTCUSDT": {
      "dir": "short",
      "conf": 0.508
    },
    "APTUSDT": {
      "dir": "long",
      "conf": 0.502
    },
    "TONUSDT": {
      "dir": "short",
      "conf": 0.504
    },
    "WLFIUSDT": {
      "dir": "short",
      "conf": 0.52
    },
    "ONDOUSDT": {
      "dir": "long",
      "conf": 0.533
    }
  },
  "equity_hist": [
    {
      "t": "2026-04-24",
      "v": 4.29
    },
    {
      "t": "2026-04-25",
      "v": 3.41
    },
    {
      "t": "2026-04-26",
      "v": 5.17
    },
    {
      "t": "2026-04-27",
      "v": 16.74
    },
    {
      "t": "2026-04-28",
      "v": 6.68
    },
    {
      "t": "2026-04-29",
      "v": 20.27
    },
    {
      "t": "2026-04-30",
      "v": 29.64
    },
    {
      "t": "2026-05-01",
      "v": 48.25
    },
    {
      "t": "2026-05-02",
      "v": 48.07
    },
    {
      "t": "2026-05-03",
      "v": 44.41
    }
  ],
  "trade_history": [
    {
      "ts": "2026-05-03 15:11",
      "symbol": "TRXUSDT",
      "side": "Buy",
      "pnl": 1.83,
      "reason": "2/9"
    },
    {
      "ts": "2026-05-03 13:46",
      "symbol": "TAOUSDT",
      "side": "Sell",
      "pnl": 0.0,
      "reason": "마진 0.0USDT < 1"
    },
    {
      "ts": "2026-05-03 13:43",
      "symbol": "TAOUSDT",
      "side": "Sell",
      "pnl": 0.11,
      "reason": "3/10"
    },
    {
      "ts": "2026-05-03 12:39",
      "symbol": "MUSDT",
      "side": "Buy",
      "pnl": -0.27,
      "reason": "1/10"
    },
    {
      "ts": "2026-05-03 10:31",
      "symbol": "MUSDT",
      "side": "Buy",
      "pnl": -0.37,
      "reason": "4/11"
    },
    {
      "ts": "2026-05-03 10:30",
      "symbol": "MUSDT",
      "side": "Buy",
      "pnl": -0.72,
      "reason": "4/11"
    },
    {
      "ts": "2026-05-03 10:20",
      "symbol": "APTUSDT",
      "side": "Buy",
      "pnl": -1.33,
      "reason": "3/9"
    },
    {
      "ts": "2026-05-03 10:20",
      "symbol": "APTUSDT",
      "side": "Buy",
      "pnl": -0.1,
      "reason": "3/9"
    },
    {
      "ts": "2026-05-03 10:03",
      "symbol": "SUIUSDT",
      "side": "Buy",
      "pnl": 0.25,
      "reason": "2/9"
    },
    {
      "ts": "2026-05-03 09:40",
      "symbol": "WLFIUSDT",
      "side": "Sell",
      "pnl": -0.47,
      "reason": "4/10"
    },
    {
      "ts": "2026-05-03 07:27",
      "symbol": "MUSDT",
      "side": "Buy",
      "pnl": 0.18,
      "reason": "3/12"
    },
    {
      "ts": "2026-05-03 06:45",
      "symbol": "DOTUSDT",
      "side": "Sell",
      "pnl": -0.0,
      "reason": "T1 진입 | GF=10 | Lv=6x | Seed=$93(9.0%)"
    },
    {
      "ts": "2026-05-03 06:37",
      "symbol": "DOTUSDT",
      "side": "Sell",
      "pnl": -1.64,
      "reason": "L4"
    },
    {
      "ts": "2026-05-03 05:37",
      "symbol": "APTUSDT",
      "side": "Sell",
      "pnl": -0.0,
      "reason": "마진 0.0USDT < 1"
    },
    {
      "ts": "2026-05-03 05:34",
      "symbol": "APTUSDT",
      "side": "Sell",
      "pnl": -0.58,
      "reason": "3/9"
    },
    {
      "ts": "2026-05-03 04:29",
      "symbol": "ADAUSDT",
      "side": "Sell",
      "pnl": -0.14,
      "reason": "3/9"
    },
    {
      "ts": "2026-05-03 03:44",
      "symbol": "MUSDT",
      "side": "Buy",
      "pnl": -0.31,
      "reason": "3/12"
    },
    {
      "ts": "2026-05-03 03:43",
      "symbol": "ONDOUSDT",
      "side": "Sell",
      "pnl": 0.21,
      "reason": "5/10"
    },
    {
      "ts": "2026-05-03 03:14",
      "symbol": "MUSDT",
      "side": "Buy",
      "pnl": 0.04,
      "reason": "2/12"
    },
    {
      "ts": "2026-05-03 03:12",
      "symbol": "PENGUUSDT",
      "side": "Buy",
      "pnl": -1.19,
      "reason": "L5"
    }
  ],
  "num_days": 10
}