{
  "ts": "2026-06-16T05:28:19.227360+09:00",
  "start_date": "2026-05-08",
  "status": "running",
  "equity": 1515.67,
  "available": 1142.8,
  "unrealized": -7.7,
  "daily_pnl": 39.61,
  "total_pnl": 580.67,
  "cum_pct": 62.1,
  "daily_avg_pct": 1.2149,
  "annual_pct": 8107.75,
  "mdd": -12.05,
  "current_dd": -4.88,
  "seed_used": 372.87,
  "seed_used_pct": 24.6,
  "long_count": 2,
  "short_count": 1,
  "positions": [
    {
      "symbol": "HYPEUSDT",
      "side": "LONG",
      "pnl": 7.01,
      "pnl_pct": 0.81,
      "margin": 125.12,
      "leverage": "7",
      "tier": "1/1",
      "entry": 66.779,
      "mark": 67.318
    },
    {
      "symbol": "WLDUSDT",
      "side": "SHORT",
      "pnl": -13.01,
      "pnl_pct": -1.52,
      "margin": 124.41,
      "leverage": "7",
      "tier": "2/2",
      "entry": 0.5896,
      "mark": 0.5985
    },
    {
      "symbol": "SOLUSDT",
      "side": "LONG",
      "pnl": -1.71,
      "pnl_pct": -0.2,
      "margin": 122.19,
      "leverage": "7",
      "tier": "1/1",
      "entry": 75.18,
      "mark": 75.03
    }
  ],
  "signals": {
    "AAVEUSDT": {
      "dir": "long",
      "conf": 0.44
    },
    "SUIUSDT": {
      "dir": "short",
      "conf": 0.551
    },
    "WLDUSDT": {
      "dir": "short",
      "conf": 0.484
    },
    "1000PEPEUSDT": {
      "dir": "short",
      "conf": 0.453
    },
    "ZECUSDT": {
      "dir": "long",
      "conf": 0.48
    },
    "HYPEUSDT": {
      "dir": "short",
      "conf": 0.509
    },
    "PENGUUSDT": {
      "dir": "long",
      "conf": 0.675
    },
    "ARBUSDT": {
      "dir": "short",
      "conf": 0.643
    },
    "ENAUSDT": {
      "dir": "short",
      "conf": 0.371
    },
    "SOLUSDT": {
      "dir": "long",
      "conf": 0.447
    },
    "BCHUSDT": {
      "dir": "short",
      "conf": 0.491
    },
    "DOTUSDT": {
      "dir": "long",
      "conf": 0.507
    },
    "XRPUSDT": {
      "dir": "short",
      "conf": 0.478
    },
    "TRXUSDT": {
      "dir": "short",
      "conf": 0.557
    },
    "BTCUSDT": {
      "dir": "neutral",
      "conf": 0.429
    },
    "BNBUSDT": {
      "dir": "neutral",
      "conf": 0.361
    },
    "TAOUSDT": {
      "dir": "short",
      "conf": 0.549
    },
    "ADAUSDT": {
      "dir": "short",
      "conf": 0.619
    },
    "LINKUSDT": {
      "dir": "long",
      "conf": 0.397
    },
    "AVAXUSDT": {
      "dir": "neutral",
      "conf": 0.43
    },
    "DOGEUSDT": {
      "dir": "neutral",
      "conf": 0.436
    },
    "NEARUSDT": {
      "dir": "short",
      "conf": 0.582
    },
    "ETHUSDT": {
      "dir": "neutral",
      "conf": 0.471
    },
    "STABLEUSDT": {
      "dir": "short",
      "conf": 0.592
    },
    "MUSDT": {
      "dir": "long",
      "conf": 0.507
    },
    "TRUMPUSDT": {
      "dir": "short",
      "conf": 0.449
    },
    "ASTERUSDT": {
      "dir": "short",
      "conf": 0.628
    },
    "XMRUSDT": {
      "dir": "long",
      "conf": 0.474
    },
    "LTCUSDT": {
      "dir": "long",
      "conf": 0.5
    },
    "APTUSDT": {
      "dir": "short",
      "conf": 0.696
    },
    "TONUSDT": {
      "dir": "short",
      "conf": 0.512
    },
    "WLFIUSDT": {
      "dir": "short",
      "conf": 0.524
    },
    "ONDOUSDT": {
      "dir": "short",
      "conf": 0.532
    },
    "DASHUSDT": {
      "dir": "short",
      "conf": 0.893
    },
    "ICPUSDT": {
      "dir": "short",
      "conf": 0.388
    },
    "1000LUNCUSDT": {
      "dir": "long",
      "conf": 0.617
    },
    "FILUSDT": {
      "dir": "long",
      "conf": 0.558
    },
    "VIRTUALUSDT": {
      "dir": "long",
      "conf": 0.526
    },
    "VVVUSDT": {
      "dir": "long",
      "conf": 0.502
    },
    "BUSDT": {
      "dir": "short",
      "conf": 0.452
    },
    "INJUSDT": {
      "dir": "short",
      "conf": 0.496
    },
    "RENDERUSDT": {
      "dir": "long",
      "conf": 0.487
    },
    "LABUSDT": {
      "dir": "long",
      "conf": 1.0
    },
    "HUSDT": {
      "dir": "long",
      "conf": 0.561
    },
    "BEATUSDT": {
      "dir": "long",
      "conf": 0.761
    },
    "SIRENUSDT": {
      "dir": "short",
      "conf": 0.573
    },
    "VELVETUSDT": {
      "dir": "long",
      "conf": 0.589
    },
    "XLMUSDT": {
      "dir": "short",
      "conf": 0.608
    }
  },
  "equity_hist": [
    {
      "t": "2026-05-15",
      "v": 27.05
    },
    {
      "t": "2026-05-16",
      "v": 38.06
    },
    {
      "t": "2026-05-17",
      "v": 36.26
    },
    {
      "t": "2026-05-18",
      "v": 52.29
    },
    {
      "t": "2026-05-19",
      "v": 52.53
    },
    {
      "t": "2026-05-20",
      "v": 47.85
    },
    {
      "t": "2026-05-21",
      "v": 47.73
    },
    {
      "t": "2026-05-22",
      "v": 67.17
    },
    {
      "t": "2026-05-23",
      "v": 78.26
    },
    {
      "t": "2026-05-24",
      "v": 202.32
    },
    {
      "t": "2026-05-25",
      "v": 210.73
    },
    {
      "t": "2026-05-26",
      "v": 189.78
    },
    {
      "t": "2026-05-27",
      "v": 163.63
    },
    {
      "t": "2026-05-28",
      "v": 233.53
    },
    {
      "t": "2026-05-29",
      "v": 281.0
    },
    {
      "t": "2026-05-30",
      "v": 288.99
    },
    {
      "t": "2026-05-31",
      "v": 277.67
    },
    {
      "t": "2026-06-01",
      "v": 337.4
    },
    {
      "t": "2026-06-02",
      "v": 335.44
    },
    {
      "t": "2026-06-03",
      "v": 398.31
    },
    {
      "t": "2026-06-04",
      "v": 415.07
    },
    {
      "t": "2026-06-05",
      "v": 546.75
    },
    {
      "t": "2026-06-06",
      "v": 533.61
    },
    {
      "t": "2026-06-07",
      "v": 585.32
    },
    {
      "t": "2026-06-08",
      "v": 561.67
    },
    {
      "t": "2026-06-09",
      "v": 538.35
    },
    {
      "t": "2026-06-10",
      "v": 491.64
    },
    {
      "t": "2026-06-11",
      "v": 625.46
    },
    {
      "t": "2026-06-12",
      "v": 429.04
    },
    {
      "t": "2026-06-13",
      "v": 439.82
    },
    {
      "t": "2026-06-14",
      "v": 371.45
    },
    {
      "t": "2026-06-15",
      "v": 597.34
    },
    {
      "t": "2026-06-16",
      "v": 580.67
    }
  ],
  "trade_history": [
    {
      "ts": "2026-06-16 04:19",
      "symbol": "SOLUSDT",
      "side": "Buy",
      "pnl": 31.01,
      "reason": "1/1"
    },
    {
      "ts": "2026-06-16 01:59",
      "symbol": "XLMUSDT",
      "side": "Buy",
      "pnl": -2.48,
      "reason": "1/2"
    },
    {
      "ts": "2026-06-16 01:55",
      "symbol": "XLMUSDT",
      "side": "Buy",
      "pnl": -1.92,
      "reason": "1/2"
    },
    {
      "ts": "2026-06-16 00:41",
      "symbol": "SOLUSDT",
      "side": "Buy",
      "pnl": 13.01,
      "reason": "-"
    },
    {
      "ts": "2026-06-15 21:17",
      "symbol": "HUSDT",
      "side": "Buy",
      "pnl": -59.66,
      "reason": "External Exit"
    },
    {
      "ts": "2026-06-15 20:40",
      "symbol": "HUSDT",
      "side": "Buy",
      "pnl": 10.09,
      "reason": "2/2"
    },
    {
      "ts": "2026-06-15 20:01",
      "symbol": "HUSDT",
      "side": "Buy",
      "pnl": 13.06,
      "reason": "1/2"
    },
    {
      "ts": "2026-06-15 19:20",
      "symbol": "HUSDT",
      "side": "Buy",
      "pnl": 18.23,
      "reason": "1/2"
    },
    {
      "ts": "2026-06-15 19:09",
      "symbol": "HYPEUSDT",
      "side": "Sell",
      "pnl": -8.12,
      "reason": "External Exit"
    },
    {
      "ts": "2026-06-15 17:52",
      "symbol": "HUSDT",
      "side": "Buy",
      "pnl": 6.83,
      "reason": "-"
    },
    {
      "ts": "2026-06-15 17:50",
      "symbol": "HUSDT",
      "side": "Buy",
      "pnl": 9.96,
      "reason": "-"
    },
    {
      "ts": "2026-06-15 16:48",
      "symbol": "HUSDT",
      "side": "Buy",
      "pnl": 64.91,
      "reason": "External Exit"
    },
    {
      "ts": "2026-06-15 16:10",
      "symbol": "HUSDT",
      "side": "Buy",
      "pnl": 13.45,
      "reason": "-"
    },
    {
      "ts": "2026-06-15 16:06",
      "symbol": "HUSDT",
      "side": "Buy",
      "pnl": 14.25,
      "reason": "-"
    },
    {
      "ts": "2026-06-15 15:16",
      "symbol": "BEATUSDT",
      "side": "Buy",
      "pnl": -21.51,
      "reason": "External Exit"
    },
    {
      "ts": "2026-06-15 12:53",
      "symbol": "HYPEUSDT",
      "side": "Buy",
      "pnl": 68.98,
      "reason": "External Exit"
    },
    {
      "ts": "2026-06-15 09:14",
      "symbol": "SOLUSDT",
      "side": "Buy",
      "pnl": 35.91,
      "reason": "External Exit"
    },
    {
      "ts": "2026-06-15 08:27",
      "symbol": "SOLUSDT",
      "side": "Buy",
      "pnl": 12.39,
      "reason": "-"
    },
    {
      "ts": "2026-06-15 00:07",
      "symbol": "SOLUSDT",
      "side": "Sell",
      "pnl": 9.61,
      "reason": "1/1"
    },
    {
      "ts": "2026-06-14 23:52",
      "symbol": "SOLUSDT",
      "side": "Sell",
      "pnl": 11.34,
      "reason": "1/1"
    }
  ],
  "num_days": 40
}